{"name":"2019-07-17 Escalade au Barrioz","index":"../","blur":[600,336],"data":[{"blur":"blurs/DSC06144.jpg","img":["imgs/DSC06144.jpg",[2000,1333]],"date":"2019-07-17 10:16","stamp":1563358613,"thumb":["thumbs/DSC06144.jpg",[168,112]]},{"img":["imgs/DSC06145.jpg",[2000,1333]],"stamp":1563358620,"date":"2019-07-17 10:17","blur":"blurs/DSC06145.jpg","thumb":["thumbs/DSC06145.jpg",[168,112]]},{"thumb":["thumbs/DSC06146.jpg",[150,225]],"date":"2019-07-17 11:25","stamp":1563362746,"img":["imgs/DSC06146.jpg",[1333,2000]],"blur":"blurs/DSC06146.jpg"},{"date":"2019-07-17 11:30","stamp":1563363058,"img":["imgs/DSC06147.jpg",[2000,1333]],"blur":"blurs/DSC06147.jpg","thumb":["thumbs/DSC06147.jpg",[168,112]]},{"thumb":["thumbs/DSC06148.jpg",[150,225]],"blur":"blurs/DSC06148.jpg","img":["imgs/DSC06148.jpg",[1333,2000]],"stamp":1563365920,"date":"2019-07-17 12:18"}],"thumb":{"max":[300,300],"min":[150,112]},"version":"1.8.2"}